<annotation>
	<folder>JPEGImages</folder>
	<filename>train_201810_image100.jpg</filename>
	<path>VOC_dipstick/JPEGImages/train_201810_image100.jpg</path>
	<source>
		<database>VOC_dipstick</database>
	</source>
	<size>
		<width>512</width>
		<height>512</height>
		<depth>3</depth>
	</size>
	<segmented>0</segmented>
	<object>
		<name>dipstick</name>
		<pose>Unspecified</pose>
		<truncated>0</truncated>
		<difficult>0</difficult>
		<bndbox>
			<xmin>197</xmin>
			<ymin>135</ymin>
			<xmax>236</xmax>
			<ymax>176</ymax>
		</bndbox>
	</object>
	<object>
		<name>dipstick</name>
		<pose>Unspecified</pose>
		<truncated>0</truncated>
		<difficult>0</difficult>
		<bndbox>
			<xmin>289</xmin>
			<ymin>164</ymin>
			<xmax>330</xmax>
			<ymax>200</ymax>
		</bndbox>
	</object>
	<object>
		<name>dipstick</name>
		<pose>Unspecified</pose>
		<truncated>0</truncated>
		<difficult>0</difficult>
		<bndbox>
			<xmin>340</xmin>
			<ymin>171</ymin>
			<xmax>382</xmax>
			<ymax>211</ymax>
		</bndbox>
	</object>
	<object>
		<name>dipstick</name>
		<pose>Unspecified</pose>
		<truncated>0</truncated>
		<difficult>0</difficult>
		<bndbox>
			<xmin>399</xmin>
			<ymin>160</ymin>
			<xmax>449</xmax>
			<ymax>200</ymax>
		</bndbox>
	</object>
	<object>
		<name>dipstick</name>
		<pose>Unspecified</pose>
		<truncated>0</truncated>
		<difficult>0</difficult>
		<bndbox>
			<xmin>409</xmin>
			<ymin>331</ymin>
			<xmax>447</xmax>
			<ymax>362</ymax>
		</bndbox>
	</object>
	<object>
		<name>dipstick</name>
		<pose>Unspecified</pose>
		<truncated>0</truncated>
		<difficult>0</difficult>
		<bndbox>
			<xmin>426</xmin>
			<ymin>299</ymin>
			<xmax>468</xmax>
			<ymax>330</ymax>
		</bndbox>
	</object>
	<object>
		<name>dipstick</name>
		<pose>Unspecified</pose>
		<truncated>0</truncated>
		<difficult>0</difficult>
		<bndbox>
			<xmin>422</xmin>
			<ymin>264</ymin>
			<xmax>461</xmax>
			<ymax>299</ymax>
		</bndbox>
	</object>
	<object>
		<name>dipstick</name>
		<pose>Unspecified</pose>
		<truncated>0</truncated>
		<difficult>0</difficult>
		<bndbox>
			<xmin>417</xmin>
			<ymin>226</ymin>
			<xmax>460</xmax>
			<ymax>264</ymax>
		</bndbox>
	</object>
	<object>
		<name>dipstick</name>
		<pose>Unspecified</pose>
		<truncated>0</truncated>
		<difficult>0</difficult>
		<bndbox>
			<xmin>242</xmin>
			<ymin>164</ymin>
			<xmax>284</xmax>
			<ymax>204</ymax>
		</bndbox>
	</object>
	<object>
		<name>dipstick</name>
		<pose>Unspecified</pose>
		<truncated>0</truncated>
		<difficult>0</difficult>
		<bndbox>
			<xmin>251</xmin>
			<ymin>204</ymin>
			<xmax>289</xmax>
			<ymax>239</ymax>
		</bndbox>
	</object>
	<object>
		<name>dipstick</name>
		<pose>Unspecified</pose>
		<truncated>0</truncated>
		<difficult>0</difficult>
		<bndbox>
			<xmin>370</xmin>
			<ymin>214</ymin>
			<xmax>416</xmax>
			<ymax>249</ymax>
		</bndbox>
	</object>
	<object>
		<name>dipstick</name>
		<pose>Unspecified</pose>
		<truncated>0</truncated>
		<difficult>0</difficult>
		<bndbox>
			<xmin>381</xmin>
			<ymin>277</ymin>
			<xmax>421</xmax>
			<ymax>307</ymax>
		</bndbox>
	</object>
	<object>
		<name>dipstick</name>
		<pose>Unspecified</pose>
		<truncated>0</truncated>
		<difficult>0</difficult>
		<bndbox>
			<xmin>367</xmin>
			<ymin>246</ymin>
			<xmax>413</xmax>
			<ymax>276</ymax>
		</bndbox>
	</object>
	<object>
		<name>dipstick</name>
		<pose>Unspecified</pose>
		<truncated>0</truncated>
		<difficult>0</difficult>
		<bndbox>
			<xmin>371</xmin>
			<ymin>303</ymin>
			<xmax>407</xmax>
			<ymax>330</ymax>
		</bndbox>
	</object>
	<object>
		<name>dipstick</name>
		<pose>Unspecified</pose>
		<truncated>0</truncated>
		<difficult>0</difficult>
		<bndbox>
			<xmin>373</xmin>
			<ymin>338</ymin>
			<xmax>409</xmax>
			<ymax>367</ymax>
		</bndbox>
	</object>
	<object>
		<name>dipstick</name>
		<pose>Unspecified</pose>
		<truncated>0</truncated>
		<difficult>0</difficult>
		<bndbox>
			<xmin>346</xmin>
			<ymin>357</ymin>
			<xmax>382</xmax>
			<ymax>384</ymax>
		</bndbox>
	</object>
	<object>
		<name>dipstick</name>
		<pose>Unspecified</pose>
		<truncated>0</truncated>
		<difficult>0</difficult>
		<bndbox>
			<xmin>321</xmin>
			<ymin>342</ymin>
			<xmax>353</xmax>
			<ymax>374</ymax>
		</bndbox>
	</object>
	<object>
		<name>dipstick</name>
		<pose>Unspecified</pose>
		<truncated>0</truncated>
		<difficult>0</difficult>
		<bndbox>
			<xmin>328</xmin>
			<ymin>287</ymin>
			<xmax>369</xmax>
			<ymax>320</ymax>
		</bndbox>
	</object>
	<object>
		<name>dipstick</name>
		<pose>Unspecified</pose>
		<truncated>0</truncated>
		<difficult>0</difficult>
		<bndbox>
			<xmin>334</xmin>
			<ymin>255</ymin>
			<xmax>376</xmax>
			<ymax>288</ymax>
		</bndbox>
	</object>
	<object>
		<name>dipstick</name>
		<pose>Unspecified</pose>
		<truncated>0</truncated>
		<difficult>0</difficult>
		<bndbox>
			<xmin>306</xmin>
			<ymin>246</ymin>
			<xmax>342</xmax>
			<ymax>280</ymax>
		</bndbox>
	</object>
	<object>
		<name>dipstick</name>
		<pose>Unspecified</pose>
		<truncated>0</truncated>
		<difficult>0</difficult>
		<bndbox>
			<xmin>328</xmin>
			<ymin>214</ymin>
			<xmax>366</xmax>
			<ymax>251</ymax>
		</bndbox>
	</object>
	<object>
		<name>dipstick</name>
		<pose>Unspecified</pose>
		<truncated>0</truncated>
		<difficult>0</difficult>
		<bndbox>
			<xmin>286</xmin>
			<ymin>217</ymin>
			<xmax>323</xmax>
			<ymax>250</ymax>
		</bndbox>
	</object>
	<object>
		<name>dipstick</name>
		<pose>Unspecified</pose>
		<truncated>0</truncated>
		<difficult>0</difficult>
		<bndbox>
			<xmin>271</xmin>
			<ymin>239</ymin>
			<xmax>305</xmax>
			<ymax>272</ymax>
		</bndbox>
	</object>
	<object>
		<name>dipstick</name>
		<pose>Unspecified</pose>
		<truncated>0</truncated>
		<difficult>0</difficult>
		<bndbox>
			<xmin>251</xmin>
			<ymin>268</ymin>
			<xmax>287</xmax>
			<ymax>295</ymax>
		</bndbox>
	</object>
	<object>
		<name>dipstick</name>
		<pose>Unspecified</pose>
		<truncated>0</truncated>
		<difficult>0</difficult>
		<bndbox>
			<xmin>287</xmin>
			<ymin>270</ymin>
			<xmax>321</xmax>
			<ymax>302</ymax>
		</bndbox>
	</object>
	<object>
		<name>dipstick</name>
		<pose>Unspecified</pose>
		<truncated>0</truncated>
		<difficult>0</difficult>
		<bndbox>
			<xmin>303</xmin>
			<ymin>299</ymin>
			<xmax>335</xmax>
			<ymax>336</ymax>
		</bndbox>
	</object>
	<object>
		<name>dipstick</name>
		<pose>Unspecified</pose>
		<truncated>0</truncated>
		<difficult>0</difficult>
		<bndbox>
			<xmin>332</xmin>
			<ymin>316</ymin>
			<xmax>370</xmax>
			<ymax>343</ymax>
		</bndbox>
	</object>
	<object>
		<name>dipstick</name>
		<pose>Unspecified</pose>
		<truncated>0</truncated>
		<difficult>0</difficult>
		<bndbox>
			<xmin>294</xmin>
			<ymin>323</ymin>
			<xmax>325</xmax>
			<ymax>347</ymax>
		</bndbox>
	</object>
	<object>
		<name>dipstick</name>
		<pose>Unspecified</pose>
		<truncated>0</truncated>
		<difficult>0</difficult>
		<bndbox>
			<xmin>264</xmin>
			<ymin>296</ymin>
			<xmax>299</xmax>
			<ymax>327</ymax>
		</bndbox>
	</object>
	<object>
		<name>dipstick</name>
		<pose>Unspecified</pose>
		<truncated>0</truncated>
		<difficult>0</difficult>
		<bndbox>
			<xmin>264</xmin>
			<ymin>323</ymin>
			<xmax>294</xmax>
			<ymax>349</ymax>
		</bndbox>
	</object>
	<object>
		<name>dipstick</name>
		<pose>Unspecified</pose>
		<truncated>0</truncated>
		<difficult>0</difficult>
		<bndbox>
			<xmin>225</xmin>
			<ymin>320</ymin>
			<xmax>262</xmax>
			<ymax>346</ymax>
		</bndbox>
	</object>
	<object>
		<name>dipstick</name>
		<pose>Unspecified</pose>
		<truncated>0</truncated>
		<difficult>0</difficult>
		<bndbox>
			<xmin>232</xmin>
			<ymin>290</ymin>
			<xmax>265</xmax>
			<ymax>328</ymax>
		</bndbox>
	</object>
	<object>
		<name>dipstick</name>
		<pose>Unspecified</pose>
		<truncated>0</truncated>
		<difficult>0</difficult>
		<bndbox>
			<xmin>193</xmin>
			<ymin>288</ymin>
			<xmax>227</xmax>
			<ymax>317</ymax>
		</bndbox>
	</object>
	<object>
		<name>dipstick</name>
		<pose>Unspecified</pose>
		<truncated>0</truncated>
		<difficult>0</difficult>
		<bndbox>
			<xmin>192</xmin>
			<ymin>313</ymin>
			<xmax>225</xmax>
			<ymax>339</ymax>
		</bndbox>
	</object>
	<object>
		<name>dipstick</name>
		<pose>Unspecified</pose>
		<truncated>0</truncated>
		<difficult>0</difficult>
		<bndbox>
			<xmin>219</xmin>
			<ymin>253</ymin>
			<xmax>253</xmax>
			<ymax>286</ymax>
		</bndbox>
	</object>
	<object>
		<name>dipstick</name>
		<pose>Unspecified</pose>
		<truncated>0</truncated>
		<difficult>0</difficult>
		<bndbox>
			<xmin>220</xmin>
			<ymin>222</ymin>
			<xmax>258</xmax>
			<ymax>257</ymax>
		</bndbox>
	</object>
	<object>
		<name>dipstick</name>
		<pose>Unspecified</pose>
		<truncated>0</truncated>
		<difficult>0</difficult>
		<bndbox>
			<xmin>218</xmin>
			<ymin>174</ymin>
			<xmax>254</xmax>
			<ymax>208</ymax>
		</bndbox>
	</object>
	<object>
		<name>dipstick</name>
		<pose>Unspecified</pose>
		<truncated>0</truncated>
		<difficult>0</difficult>
		<bndbox>
			<xmin>178</xmin>
			<ymin>161</ymin>
			<xmax>210</xmax>
			<ymax>204</ymax>
		</bndbox>
	</object>
	<object>
		<name>dipstick</name>
		<pose>Unspecified</pose>
		<truncated>0</truncated>
		<difficult>0</difficult>
		<bndbox>
			<xmin>198</xmin>
			<ymin>199</ymin>
			<xmax>230</xmax>
			<ymax>235</ymax>
		</bndbox>
	</object>
	<object>
		<name>dipstick</name>
		<pose>Unspecified</pose>
		<truncated>0</truncated>
		<difficult>0</difficult>
		<bndbox>
			<xmin>151</xmin>
			<ymin>300</ymin>
			<xmax>188</xmax>
			<ymax>332</ymax>
		</bndbox>
	</object>
	<object>
		<name>dipstick</name>
		<pose>Unspecified</pose>
		<truncated>0</truncated>
		<difficult>0</difficult>
		<bndbox>
			<xmin>177</xmin>
			<ymin>241</ymin>
			<xmax>217</xmax>
			<ymax>280</ymax>
		</bndbox>
	</object>
<count>41</count></annotation>